plugins/__init__.py
plugins/datepicker/__init__.py
plugins/datepicker/apps.py
plugins/datepicker/static/datepicker/jqueryui_datepicker_508.js
plugins/datepicker/static/images/ui-icons_444444_256x240.png
plugins/datepicker/static/images/ui-icons_555555_256x240.png
plugins/datepicker/static/images/ui-icons_777620_256x240.png
plugins/datepicker/static/images/ui-icons_777777_256x240.png
plugins/datepicker/static/images/ui-icons_cc0000_256x240.png
plugins/datepicker/static/images/ui-icons_ffffff_256x240.png
plugins/datepicker/static/jquery-ui/jquery-ui.css
plugins/datepicker/static/jquery-ui/jquery-ui.js
plugins/datepicker/static/jquery-ui/jquery-ui.min.css
plugins/datepicker/static/jquery-ui/jquery-ui.min.js
plugins/datepicker/static/jquery-ui/jquery-ui.structure.min.css
plugins/datepicker/static/jquery-ui/jquery-ui.theme.min.css
plugins/datepicker/static/jquery-ui/images/ui-icons_444444_256x240.png
plugins/datepicker/static/jquery-ui/images/ui-icons_555555_256x240.png
plugins/datepicker/static/jquery-ui/images/ui-icons_777620_256x240.png
plugins/datepicker/static/jquery-ui/images/ui-icons_777777_256x240.png
plugins/datepicker/static/jquery-ui/images/ui-icons_cc0000_256x240.png
plugins/datepicker/static/jquery-ui/images/ui-icons_ffffff_256x240.png
plugins/select2/__init__.py
plugins/select2/apps.py
plugins/select2/static/select2/select2-bootstrap.css
plugins/select2/static/select2/select2-spinner.gif
plugins/select2/static/select2/select2.css
plugins/select2/static/select2/select2.js
plugins/select2/static/select2/select2.png
plugins/select2/static/select2/select2_locale_ar.js
plugins/select2/static/select2/select2_locale_az.js
plugins/select2/static/select2/select2_locale_bg.js
plugins/select2/static/select2/select2_locale_ca.js
plugins/select2/static/select2/select2_locale_cs.js
plugins/select2/static/select2/select2_locale_da.js
plugins/select2/static/select2/select2_locale_de.js
plugins/select2/static/select2/select2_locale_el.js
django_508_plugins-3.0.2.dist-info/METADATA
django_508_plugins-3.0.2.dist-info/WHEEL
django_508_plugins-3.0.2.dist-info/RECORD
