Metadata-Version: 2.4
Name: django-508-plugins
Version: 3.0.2
Summary: Installable Django app containing 508-compliant plugins.
Project-URL: Homepage, https://github.com/imsweb/django-508-plugins
Author-email: Brad Rutten <ruttenb@imsweb.com>
Maintainer-email: Brad Rutten <ruttenb@imsweb.com>, Jacob Tomlinson <tomlinsonj@imsweb.com>
License-Expression: MIT
Classifier: Development Status :: 5 - Production/Stable
Classifier: Intended Audience :: Developers
Classifier: License :: OSI Approved :: MIT License
Classifier: Operating System :: OS Independent
Classifier: Programming Language :: Python
Classifier: Topic :: Utilities
